{"coordinateSystem":"origin top-left; +x right; +y down","mode":"playing","level":1,"levelTotal":20,"levelName":"Dustline Entry","timer":58.62,"score":338,"kills":4,"combo":1,"muted":false,"objective":{"type":"eliminate","title":"Bounty Sweep","progress":4,"target":9,"statusText":"Hostiles 4/9"},"player":{"x":228.3,"y":410.5,"hp":72,"maxHp":100,"dashCooldown":0,"weapon":"Sidearm"},"enemies":[{"type":"raider","x":179.4,"y":267,"hp":44},{"type":"raider","x":111.7,"y":347.7,"hp":44},{"type":"raider","x":209.9,"y":346.1,"hp":44},{"type":"raider","x":176,"y":267.7,"hp":44}],"bullets":{"player":1,"enemy":0},"map":{"district":"rust","obstacleCount":9},"upgradesOffered":[]}