{"coordinateSystem":"origin top-left; +x right; +y down","mode":"playing","level":1,"levelTotal":20,"levelName":"Dustline Entry","timer":50.7,"score":358,"kills":4,"combo":0,"muted":false,"objective":{"type":"eliminate","title":"Bounty Sweep","description":"Eliminate all hostiles","progress":4,"target":5,"statusText":"Hostiles 4/5"},"player":{"x":339.2,"y":491.2,"hp":78.2,"maxHp":100,"dashCooldown":0,"weapon":"Sidearm"},"enemies":[{"type":"raider","x":146.4,"y":193.4,"hp":44}],"bullets":{"player":0,"enemy":0},"map":{"district":"rust","obstacleCount":9},"upgradesOffered":[]}