{"coordinateSystem":"origin top-left; +x right; +y down","mode":"playing","level":1,"levelTotal":20,"levelName":"Dustline Entry","timer":67.22,"score":0,"kills":0,"combo":0,"muted":false,"objective":{"type":"eliminate","title":"Bounty Sweep","description":"Eliminate all hostiles","progress":0,"target":5,"statusText":"Hostiles 0/5"},"player":{"x":180,"y":458,"hp":100,"maxHp":100,"dashCooldown":0,"weapon":"Sidearm"},"enemies":[{"type":"raider","x":117.7,"y":302.2,"hp":44},{"type":"raider","x":124,"y":263.7,"hp":44}],"bullets":{"player":0,"enemy":0},"map":{"district":"rust","obstacleCount":9},"upgradesOffered":[]}